pather/__init__.py
pather-0.2.2.dist-info/LICENSE
pather-0.2.2.dist-info/WHEEL
pather-0.2.2.dist-info/METADATA
pather-0.2.2.dist-info/RECORD
