Metadata-Version: 2.1
Name: pather
Version: 0.2.2
Summary: Make path from string!
Author-email: Alexander Bogatyrev <alexander@bogatyrev.de>
Requires-Python: >=3.6
Classifier: License :: OSI Approved :: MIT License
Project-URL: Home, https://github.com/bogatyrev74/pather
